movva_tools/__init__.py
movva_tools/base_exception.py
movva_tools/constants.py
movva_tools/databases.py
movva_tools/decorators.py
movva_tools/examples/copy_flow_example.py
movva_tools/examples/import_contacts_example.py
movva_tools/exceptions.py
movva_tools/import_contacts.py
movva_tools/integrations/__init__.py
movva_tools/integrations/google.py
movva_tools/integrations/google_drive.py
movva_tools/integrations/google_spreadsheets.py
movva_tools/models/__init__.py
movva_tools/models/api_token_model.py
movva_tools/models/campaign_models.py
movva_tools/models/channel_models.py
movva_tools/models/contacts_models.py
movva_tools/models/flow_models.py
movva_tools/models/messages_models.py
movva_tools/models/organization_models.py
movva_tools/models/user_models.py
movva_tools/notifications/__init__.py
movva_tools/notifications/slack.py
movva_tools/parsers.py
movva_tools/serializers/__init__.py
movva_tools/serializers/base_serializer.py
movva_tools/serializers/campaign_event_serializer.py
movva_tools/serializers/campaign_serializer.py
movva_tools/serializers/contact_group_serializer.py
movva_tools/serializers/flow_revision_serializer.py
movva_tools/serializers/flow_serializer.py
movva_tools/serializers/organization_serializer.py
movva_tools/services/__init__.py
movva_tools/services/api_token_service.py
movva_tools/services/base_service.py
movva_tools/services/campaign_service.py
movva_tools/services/channel_service.py
movva_tools/services/contacts_service.py
movva_tools/services/flow_service.py
movva_tools/services/messages_service.py
movva_tools/services/organization_service.py
movva_tools/services/user_service.py
movva_tools/utils.py
movva_tools/validators.py
movva_tools-2.2.1.dist-info/METADATA
movva_tools-2.2.1.dist-info/WHEEL
movva_tools-2.2.1.dist-info/RECORD
