Metadata-Version: 2.1
Name: movva_tools
Version: 2.2.1
Summary: Package that contains integrations and tools to use in issues of Movva organization.
Author: WillamesCampos
Author-email: willwjccampos@gmail.com
Requires-Python: >=3.10,<4.0
Classifier: Programming Language :: Python :: 3
Classifier: Programming Language :: Python :: 3.10
Classifier: Programming Language :: Python :: 3.11
Requires-Dist: aiohttp (>=3.8.5,<4.0.0)
Requires-Dist: aiopg (>=1.4.0,<2.0.0)
Requires-Dist: asyncpg (>=0.29.0,<0.30.0)
Requires-Dist: flask (>=3.0.0,<4.0.0)
Requires-Dist: google-api-python-client (>=2.95.0,<3.0.0)
Requires-Dist: google-auth-httplib2 (>=0.1.0,<0.2.0)
Requires-Dist: google-auth-oauthlib (>=1.0.0,<2.0.0)
Requires-Dist: google-cloud-secret-manager (>=2.16.4,<3.0.0)
Requires-Dist: loguru (>=0.7.0,<0.8.0)
Requires-Dist: marshmallow (>=3.20.1,<4.0.0)
Requires-Dist: more-itertools (>=10.0.0,<11.0.0)
Requires-Dist: openpyxl (>=3.1.2,<4.0.0)
Requires-Dist: pandas (>=2.0.3,<3.0.0)
Requires-Dist: psycopg2-binary (>=2.9.8,<3.0.0)
Requires-Dist: pytest (>=7.4.3,<8.0.0)
Requires-Dist: rapidpro-python (>=2.12.0,<3.0.0)
Requires-Dist: sqlalchemy (>=2.0.20,<3.0.0)
